h2o4gpu-0.4.1.data/purelib/_ch2o4gpu_cpu.so
h2o4gpu-0.4.1.data/purelib/_ch2o4gpu_gpu.so
h2o4gpu-0.4.1.data/purelib/docs/Makefile
h2o4gpu-0.4.1.data/purelib/docs/conf.py
h2o4gpu-0.4.1.data/purelib/docs/h2o4gpu.rst
h2o4gpu-0.4.1.data/purelib/docs/h2o4gpu.solvers.rst
h2o4gpu-0.4.1.data/purelib/docs/h2o4gpu.util.rst
h2o4gpu-0.4.1.data/purelib/docs/index.rst
h2o4gpu-0.4.1.data/purelib/docs/intro.rst
h2o4gpu-0.4.1.data/purelib/docs/make.bat
h2o4gpu-0.4.1.data/purelib/docs/_static/style.css
h2o4gpu-0.4.1.data/purelib/h2o4gpu/BUILD_INFO.txt
h2o4gpu-0.4.1.data/purelib/h2o4gpu/__init__.base.py
h2o4gpu-0.4.1.data/purelib/h2o4gpu/__init__.py
h2o4gpu-0.4.1.data/purelib/h2o4gpu/_config.py
h2o4gpu-0.4.1.data/purelib/h2o4gpu/_isotonic.cpython-36m-powerpc64le-linux-gnu.so
h2o4gpu-0.4.1.data/purelib/h2o4gpu/base.py
h2o4gpu-0.4.1.data/purelib/h2o4gpu/calibration.py
h2o4gpu-0.4.1.data/purelib/h2o4gpu/conftest.py
h2o4gpu-0.4.1.data/purelib/h2o4gpu/discriminant_analysis.py
h2o4gpu-0.4.1.data/purelib/h2o4gpu/dummy.py
h2o4gpu-0.4.1.data/purelib/h2o4gpu/exceptions.py
h2o4gpu-0.4.1.data/purelib/h2o4gpu/h2o4gpu_exceptions.py
h2o4gpu-0.4.1.data/purelib/h2o4gpu/isotonic.py
h2o4gpu-0.4.1.data/purelib/h2o4gpu/kernel_approximation.py
h2o4gpu-0.4.1.data/purelib/h2o4gpu/kernel_ridge.py
h2o4gpu-0.4.1.data/purelib/h2o4gpu/multiclass.py
h2o4gpu-0.4.1.data/purelib/h2o4gpu/multioutput.py
h2o4gpu-0.4.1.data/purelib/h2o4gpu/naive_bayes.py
h2o4gpu-0.4.1.data/purelib/h2o4gpu/pipeline.py
h2o4gpu-0.4.1.data/purelib/h2o4gpu/random_projection.py
h2o4gpu-0.4.1.data/purelib/h2o4gpu/setup.py
h2o4gpu-0.4.1.data/purelib/h2o4gpu/types.py
h2o4gpu-0.4.1.data/purelib/h2o4gpu/__check_build/__init__.py
h2o4gpu-0.4.1.data/purelib/h2o4gpu/__check_build/_check_build.cpython-36m-powerpc64le-linux-gnu.so
h2o4gpu-0.4.1.data/purelib/h2o4gpu/__check_build/setup.py
h2o4gpu-0.4.1.data/purelib/h2o4gpu/_build_utils/__init__.py
h2o4gpu-0.4.1.data/purelib/h2o4gpu/_build_utils/openmp_helpers.py
h2o4gpu-0.4.1.dist-info/METADATA
h2o4gpu-0.4.1.dist-info/WHEEL
h2o4gpu-0.4.1.dist-info/top_level.txt
h2o4gpu-0.4.1.dist-info/RECORD
