Metadata-Version: 2.1
Name: h2o4gpu
Version: 0.4.1
Summary: H2O.ai GPU Edition
Home-page: http://h2o.ai
Author: H2O.ai, Inc.
Author-email: h2ostream@googlegroups.com
License: Apache v2.0
Platform: UNKNOWN
Requires-Dist: pandas (>=0.24.2)
Requires-Dist: numpy (>=1.16.4)
Requires-Dist: python-dateutil (>=2.7.2)
Requires-Dist: pytz (>=2018.4)
Requires-Dist: scipy (>=1.3.1)
Requires-Dist: tabulate (>=0.8.2)
Requires-Dist: future (>=0.16.0)
Requires-Dist: psutil (>=5.6.3)
Requires-Dist: joblib (>=0.14.0)
Requires-Dist: scikit-learn (==0.21.2)
